odoo10_addon_account_invoice_overdue_reminder-10.0.2.0.2.99.dev6-py3.8-nspkg.pth
odoo/addons/account_invoice_overdue_reminder/README.rst
odoo/addons/account_invoice_overdue_reminder/__init__.py
odoo/addons/account_invoice_overdue_reminder/__manifest__.py
odoo/addons/account_invoice_overdue_reminder/data/mail_template.xml
odoo/addons/account_invoice_overdue_reminder/data/overdue_reminder_result.xml
odoo/addons/account_invoice_overdue_reminder/i18n/fr.po
odoo/addons/account_invoice_overdue_reminder/migrations/10.0.2.0.1/pre-migration.py
odoo/addons/account_invoice_overdue_reminder/migrations/10.0.2.0.2/pre-migration.py
odoo/addons/account_invoice_overdue_reminder/models/__init__.py
odoo/addons/account_invoice_overdue_reminder/models/account_invoice.py
odoo/addons/account_invoice_overdue_reminder/models/account_invoice_overdue_reminder.py
odoo/addons/account_invoice_overdue_reminder/models/company.py
odoo/addons/account_invoice_overdue_reminder/models/config_settings.py
odoo/addons/account_invoice_overdue_reminder/models/overdue_reminder_action.py
odoo/addons/account_invoice_overdue_reminder/models/overdue_reminder_result.py
odoo/addons/account_invoice_overdue_reminder/models/partner.py
odoo/addons/account_invoice_overdue_reminder/readme/CONFIGURATION.rst
odoo/addons/account_invoice_overdue_reminder/readme/CONTRIBUTORS.rst
odoo/addons/account_invoice_overdue_reminder/readme/DESCRIPTION.rst
odoo/addons/account_invoice_overdue_reminder/readme/USAGE.rst
odoo/addons/account_invoice_overdue_reminder/security/ir.model.access.csv
odoo/addons/account_invoice_overdue_reminder/security/rule.xml
odoo/addons/account_invoice_overdue_reminder/static/description/icon.png
odoo/addons/account_invoice_overdue_reminder/static/description/index.html
odoo/addons/account_invoice_overdue_reminder/views/account_invoice.xml
odoo/addons/account_invoice_overdue_reminder/views/account_invoice_overdue_reminder.xml
odoo/addons/account_invoice_overdue_reminder/views/config_settings.xml
odoo10_addon_account_invoice_overdue_reminder-10.0.2.0.2.99.dev6.dist-info/METADATA
odoo10_addon_account_invoice_overdue_reminder-10.0.2.0.2.99.dev6.dist-info/WHEEL
odoo10_addon_account_invoice_overdue_reminder-10.0.2.0.2.99.dev6.dist-info/namespace_packages.txt
odoo10_addon_account_invoice_overdue_reminder-10.0.2.0.2.99.dev6.dist-info/top_level.txt
odoo10_addon_account_invoice_overdue_reminder-10.0.2.0.2.99.dev6.dist-info/RECORD
